pyarinc424/__init__.py
pyarinc424/arinc.py
pyarinc424/config.py
pyarinc424/database.py
pyarinc424/main.py
pyarinc424/record_maps.py
pyarinc424-0.4.0.dist-info/licenses/LICENSE
pyarinc424-0.4.0.dist-info/METADATA
pyarinc424-0.4.0.dist-info/WHEEL
pyarinc424-0.4.0.dist-info/entry_points.txt
pyarinc424-0.4.0.dist-info/top_level.txt
pyarinc424-0.4.0.dist-info/RECORD
