Metadata-Version: 2.4
Name: pyarinc424
Version: 0.4.0
Summary: Python library for parsing ARINC 424 data
Requires-Python: >=3.11
License-File: LICENSE
Requires-Dist: psycopg2-binary>=2.9.10
Requires-Dist: rich>=14.0.0
Dynamic: license-file
